{
    "title": "Average cleaning time in W3C SVG 1.1 TestSuite",
    "items_font": {
        "family": "Arial",
        "size": 12
    },
    "items": [
        {
            "name": "svgcleaner 0.10.0",
            "value": 1.6
        },
        {
            "name": "svgo 0.7.2",
            "value": 215
        },
        {
            "name": "scour 0.35",
            "value": 137
        }
    ],
    "hor_axis": {
        "title": "Time",
        "width": 500,
        "suffix": "ms"
    }
}
